drb_impl_zarr/__init__.py
drb_impl_zarr/_version.py
drb_impl_zarr/cortex.yml
drb_impl_zarr/exceptions.py
drb_impl_zarr/zarr_data_set_node.py
drb_impl_zarr/zarr_node_factory.py
drb_impl_zarr-1.0.0.data/data/requirements.txt
drb_impl_zarr-1.0.0.dist-info/METADATA
drb_impl_zarr-1.0.0.dist-info/WHEEL
drb_impl_zarr-1.0.0.dist-info/entry_points.txt
drb_impl_zarr-1.0.0.dist-info/top_level.txt
drb_impl_zarr-1.0.0.dist-info/RECORD
