Metadata-Version: 2.1
Name: drb-impl-zarr
Version: 1.0.0
Summary: DRB Zarr implementation
Home-page: https://gitlab.com/drb-python/impl/zarr
Author: GAEL Systems
Author-email: drb-python@gael.fr
License: UNKNOWN
Platform: UNKNOWN
Classifier: Programming Language :: Python :: 3.8
Classifier: License :: OSI Approved :: Apache Software License
Classifier: Operating System :: OS Independent
Requires-Python: >=3.8
Requires-Dist: drb (<1.1.0,>=1.0.1)
Requires-Dist: drb-impl-zip (==1.0.0)
Requires-Dist: drb-impl-file (==1.0.0)
Requires-Dist: fsspec
Requires-Dist: aiohttp
Requires-Dist: versioneer (~=0.21)
Requires-Dist: zarr (~=2.10.2)
